{
	"id": "JutoGpZkiNAAdYJ",
	"json": "{\"id\":\"JutoGpZkiNAAdYJ\",\"url\":\"https://hard.rozetka.com.ua/ua/videocards/c80087/\",\"loadedUrl\":\"https://hard.rozetka.com.ua/ua/videocards/c80087/\",\"uniqueKey\":\"https://hard.rozetka.com.ua/ua/videocards/c80087\",\"method\":\"GET\",\"noRetry\":false,\"retryCount\":0,\"errorMessages\":[],\"headers\":{},\"userData\":{\"__crawlee\":{\"state\":4}},\"handledAt\":\"2026-03-20T09:57:05.384Z\"}",
	"method": "GET",
	"orderNo": null,
	"retryCount": 0,
	"uniqueKey": "https://hard.rozetka.com.ua/ua/videocards/c80087",
	"url": "https://hard.rozetka.com.ua/ua/videocards/c80087/"
}